conci/__init__.py
conci/main.py
conci-0.0.1.dist-info/METADATA
conci-0.0.1.dist-info/WHEEL
conci-0.0.1.dist-info/RECORD
