Metadata-Version: 2.4
Name: conci
Version: 0.0.1
Summary: A Python library for enabling self-awareness in machines.
Author-email: Kevin Saltarelli <kevinqz@gmail.com>
Requires-Python: >=3.8
Requires-Dist: pydantic>=2.10.6
Requires-Dist: requests>=2.25
Provides-Extra: all
Requires-Dist: black>=22.0; extra == 'all'
Requires-Dist: mypy>=1.0; extra == 'all'
Requires-Dist: pytest-cov>=4.0; extra == 'all'
Requires-Dist: pytest>=7.0; extra == 'all'
Requires-Dist: ruff>=0.1; extra == 'all'
Provides-Extra: dev
Requires-Dist: black>=22.0; extra == 'dev'
Requires-Dist: mypy>=1.0; extra == 'dev'
Requires-Dist: pytest-cov>=4.0; extra == 'dev'
Requires-Dist: pytest>=7.0; extra == 'dev'
Requires-Dist: ruff>=0.1; extra == 'dev'
Provides-Extra: docs
Provides-Extra: test
Requires-Dist: pytest-cov>=4.0; extra == 'test'
Requires-Dist: pytest>=7.0; extra == 'test'
